{"name":"build-javascript","namedChunkGroups":{"polyfill":{"name":"polyfill","assets":[{"name":"webpack-runtime-44864b15c49a2d37fc3c.js","size":5612},{"name":"polyfill-e46dd9e24f80b3a7ad2b.js","size":85834}],"filteredAssets":0,"assetsSize":91446,"filteredAuxiliaryAssets":2,"auxiliaryAssetsSize":228796},"app":{"name":"app","assets":[{"name":"webpack-runtime-44864b15c49a2d37fc3c.js","size":5612},{"name":"styles.20835e019f1fcd2f4cef.css","size":82185},{"name":"framework-a9015175e98d25bbe9ef.js","size":129726},{"name":"app-7a8a072e28852ff9324c.js","size":148639}],"filteredAssets":0,"assetsSize":366162,"filteredAuxiliaryAssets":6,"auxiliaryAssetsSize":1046846},"component---src-pages-404-tsx":{"name":"component---src-pages-404-tsx","assets":[{"name":"styles.20835e019f1fcd2f4cef.css","size":82185},{"name":"commons-67877720207a936c7b15.js","size":104831},{"name":"component---src-pages-404-tsx-4b25e2dfcd7910a7efce.js","size":575}],"filteredAssets":0,"assetsSize":187591,"filteredAuxiliaryAssets":5,"auxiliaryAssetsSize":483370},"component---src-pages-contact-tsx":{"name":"component---src-pages-contact-tsx","assets":[{"name":"styles.20835e019f1fcd2f4cef.css","size":82185},{"name":"commons-67877720207a936c7b15.js","size":104831},{"name":"component---src-pages-contact-tsx-a6ca7aeba1abe212f8cb.js","size":1176}],"filteredAssets":0,"assetsSize":188192,"filteredAuxiliaryAssets":5,"auxiliaryAssetsSize":484437},"component---src-pages-faq-tsx":{"name":"component---src-pages-faq-tsx","assets":[{"name":"styles.20835e019f1fcd2f4cef.css","size":82185},{"name":"commons-67877720207a936c7b15.js","size":104831},{"name":"component---src-pages-faq-tsx-d7013f677d94cca531c3.js","size":2642}],"filteredAssets":0,"assetsSize":189658,"filteredAuxiliaryAssets":5,"auxiliaryAssetsSize":485901},"component---src-pages-how-it-works-tsx":{"name":"component---src-pages-how-it-works-tsx","assets":[{"name":"styles.20835e019f1fcd2f4cef.css","size":82185},{"name":"commons-67877720207a936c7b15.js","size":104831},{"name":"component---src-pages-how-it-works-tsx-0811188da00894f1aa9c.js","size":8346}],"filteredAssets":0,"assetsSize":195362,"filteredAuxiliaryAssets":5,"auxiliaryAssetsSize":486355},"component---src-pages-index-tsx":{"name":"component---src-pages-index-tsx","assets":[{"name":"styles.20835e019f1fcd2f4cef.css","size":82185},{"name":"commons-67877720207a936c7b15.js","size":104831},{"name":"component---src-pages-index-tsx-286e5a1b6901ade44c89.js","size":1312}],"filteredAssets":0,"assetsSize":188328,"filteredAuxiliaryAssets":5,"auxiliaryAssetsSize":484496},"component---src-pages-news-tsx":{"name":"component---src-pages-news-tsx","assets":[{"name":"styles.20835e019f1fcd2f4cef.css","size":82185},{"name":"commons-67877720207a936c7b15.js","size":104831},{"name":"component---src-pages-news-tsx-e4194e1eddfd5f957547.js","size":5147}],"filteredAssets":0,"assetsSize":192163,"filteredAuxiliaryAssets":5,"auxiliaryAssetsSize":489274},"component---src-pages-privacy-policy-tsx":{"name":"component---src-pages-privacy-policy-tsx","assets":[{"name":"styles.20835e019f1fcd2f4cef.css","size":82185},{"name":"commons-67877720207a936c7b15.js","size":104831},{"name":"component---src-pages-privacy-policy-tsx-739b1f5380d0cd9a3758.js","size":5985}],"filteredAssets":0,"assetsSize":193001,"filteredAuxiliaryAssets":5,"auxiliaryAssetsSize":489967},"component---src-pages-terms-of-use-tsx":{"name":"component---src-pages-terms-of-use-tsx","assets":[{"name":"styles.20835e019f1fcd2f4cef.css","size":82185},{"name":"commons-67877720207a936c7b15.js","size":104831},{"name":"component---src-pages-terms-of-use-tsx-cbd846674d1925167c91.js","size":35803}],"filteredAssets":0,"assetsSize":222819,"filteredAuxiliaryAssets":5,"auxiliaryAssetsSize":525975},"component---src-pages-try-now-tsx":{"name":"component---src-pages-try-now-tsx","assets":[{"name":"styles.20835e019f1fcd2f4cef.css","size":82185},{"name":"commons-67877720207a936c7b15.js","size":104831},{"name":"component---src-pages-try-now-tsx-fc5e2eef1334dab760a0.js","size":23980}],"filteredAssets":0,"assetsSize":210996,"filteredAuxiliaryAssets":5,"auxiliaryAssetsSize":568971},"component---src-templates-blog-post-index-tsx":{"name":"component---src-templates-blog-post-index-tsx","assets":[{"name":"styles.20835e019f1fcd2f4cef.css","size":82185},{"name":"commons-67877720207a936c7b15.js","size":104831},{"name":"component---src-templates-blog-post-index-tsx-c1ccfa857e33d634eafb.js","size":4950}],"filteredAssets":0,"assetsSize":191966,"filteredAuxiliaryAssets":5,"auxiliaryAssetsSize":496266},"component---src-templates-tag-page-index-tsx":{"name":"component---src-templates-tag-page-index-tsx","assets":[{"name":"styles.20835e019f1fcd2f4cef.css","size":82185},{"name":"commons-67877720207a936c7b15.js","size":104831},{"name":"component---src-templates-tag-page-index-tsx-380ac10df4a3d66f7aba.js","size":946}],"filteredAssets":0,"assetsSize":187962,"filteredAuxiliaryAssets":5,"auxiliaryAssetsSize":484828}},"assetsByChunkName":{"polyfill":["webpack-runtime-44864b15c49a2d37fc3c.js","polyfill-e46dd9e24f80b3a7ad2b.js"],"app":["webpack-runtime-44864b15c49a2d37fc3c.js","styles.20835e019f1fcd2f4cef.css","framework-a9015175e98d25bbe9ef.js","app-7a8a072e28852ff9324c.js"],"component---src-pages-404-tsx":["styles.20835e019f1fcd2f4cef.css","commons-67877720207a936c7b15.js","component---src-pages-404-tsx-4b25e2dfcd7910a7efce.js"],"component---src-pages-contact-tsx":["styles.20835e019f1fcd2f4cef.css","commons-67877720207a936c7b15.js","component---src-pages-contact-tsx-a6ca7aeba1abe212f8cb.js"],"component---src-pages-faq-tsx":["styles.20835e019f1fcd2f4cef.css","commons-67877720207a936c7b15.js","component---src-pages-faq-tsx-d7013f677d94cca531c3.js"],"component---src-pages-how-it-works-tsx":["styles.20835e019f1fcd2f4cef.css","commons-67877720207a936c7b15.js","component---src-pages-how-it-works-tsx-0811188da00894f1aa9c.js"],"component---src-pages-index-tsx":["styles.20835e019f1fcd2f4cef.css","commons-67877720207a936c7b15.js","component---src-pages-index-tsx-286e5a1b6901ade44c89.js"],"component---src-pages-news-tsx":["styles.20835e019f1fcd2f4cef.css","commons-67877720207a936c7b15.js","component---src-pages-news-tsx-e4194e1eddfd5f957547.js"],"component---src-pages-privacy-policy-tsx":["styles.20835e019f1fcd2f4cef.css","commons-67877720207a936c7b15.js","component---src-pages-privacy-policy-tsx-739b1f5380d0cd9a3758.js"],"component---src-pages-terms-of-use-tsx":["styles.20835e019f1fcd2f4cef.css","commons-67877720207a936c7b15.js","component---src-pages-terms-of-use-tsx-cbd846674d1925167c91.js"],"component---src-pages-try-now-tsx":["styles.20835e019f1fcd2f4cef.css","commons-67877720207a936c7b15.js","component---src-pages-try-now-tsx-fc5e2eef1334dab760a0.js"],"component---src-templates-blog-post-index-tsx":["styles.20835e019f1fcd2f4cef.css","commons-67877720207a936c7b15.js","component---src-templates-blog-post-index-tsx-c1ccfa857e33d634eafb.js"],"component---src-templates-tag-page-index-tsx":["styles.20835e019f1fcd2f4cef.css","commons-67877720207a936c7b15.js","component---src-templates-tag-page-index-tsx-380ac10df4a3d66f7aba.js"]},"childAssetsByChunkName":{}}